devtopy/__init__.py
devtopy/_devtopy.py
devtopy/exception.py
devtopy/model.py
devtopy/module/__init__.py
devtopy/module/_article.py
devtopy/module/_comments.py
devtopy/module/_followed_tags.py
devtopy/module/_organizations.py
devtopy/module/_podcast_episodes.py
devtopy/module/_profile_images.py
devtopy/module/_reactions.py
devtopy/module/_tags.py
devtopy/module/_users.py
devtopy/module/_videos.py
devtopy-0.1.1.dist-info/METADATA
devtopy-0.1.1.dist-info/WHEEL
devtopy-0.1.1.dist-info/licenses/LICENSE
devtopy-0.1.1.dist-info/RECORD
