Metadata-Version: 2.3
Name: devtopy
Version: 0.1.1
Summary: A Python client library for interacting with the dev.to API. Easily access key dev.to features including article retrieval, posting, and user information management.
Project-URL: Homepage, https://github.com/rmc8/devtopy
Author-email: "rmc-8.com" <kmyashi@rmc-8.com>
License-File: LICENSE
Requires-Python: >=3.8
Requires-Dist: pydantic>=2.8.2
Requires-Dist: requests>=2.32.3
